LNPLPL_functions.py
LNPL_functions.py
pdf_fitter.py
pdffit-0.1.dist-info/LICENSE
pdffit-0.1.dist-info/METADATA
pdffit-0.1.dist-info/WHEEL
pdffit-0.1.dist-info/top_level.txt
pdffit-0.1.dist-info/RECORD
