Metadata-Version: 2.1
Name: pdffit
Version: 0.1
Summary: Fit a Lognormal + Power law distribution to data
Home-page: https://github.com/shivankhullar/PDF_Fit
Author: Shivan Khullar
Author-email: shivankhullar@gmail.com
License: UNKNOWN
Platform: UNKNOWN
Classifier: Programming Language :: Python :: 3.8
Classifier: License :: OSI Approved :: MIT License
Requires-Dist: numpy (>=1.0)
Requires-Dist: scipy (>=1.0)
